<?xml version="1.0" encoding="UTF-8"?>
<Export generator="IRIS" version="26" zv="IRIS for UNIX (Red Hat Enterprise Linux for x86-64) 2021.1 (Build 215U)" ts="2021-11-29 15:49:11">
<Global>
<Node><Sub>^EnsLib.PubSub.DomainNameD</Sub>
<Node><Sub>HLHT</Sub>
<DataBase64>AgEGAUhMSFQCAQ==
</DataBase64>
</Node>
</Node>
</Global>


<Global>
<Node><Sub>^EnsLib.PubSub.SubscriptionD</Sub>
<Data>99</Data>
<Node><Sub>24</Sub>
<DataBase64>AgEGAUhMSFQBAQEEATIwEAFEb2N1bWVudEFjY2Vzcw==
</DataBase64>
</Node>
<Node><Sub>25</Sub>
<DataBase64>AgEGAUhMSFQBAQEEATIxEgFEb2N1bWVudFJldHJpZXZl
</DataBase64>
</Node>
<Node><Sub>26</Sub>
<DataBase64>AgEGAUhMSFQBAQEEATE5EgFEb2N1bWVudFJlZ2lzdGVy
</DataBase64>
</Node>
<Node><Sub>99</Sub>
<DataBase64>AgEGAUhMSFQBAQEEATg3FQFQYXRpZW50SW5mb1JlZ2lzdGVy
</DataBase64>
</Node>
</Node>
</Global>


<Global>
<Node><Sub>^EnsLib.PubSub.SubscriptionI</Sub>
<Node><Sub>TopicIndex</Sub>
<Node><Sub> HLHT</Sub>
<Node><Sub> DOCUMENTACCESS</Sub>
<Node><Sub>20</Sub>
<Node><Sub>24</Sub>
<Data></Data>
</Node>
</Node>
</Node>
<Node><Sub> DOCUMENTREGISTER</Sub>
<Node><Sub>19</Sub>
<Node><Sub>26</Sub>
<Data></Data>
</Node>
</Node>
</Node>
<Node><Sub> DOCUMENTRETRIEVE</Sub>
<Node><Sub>21</Sub>
<Node><Sub>25</Sub>
<Data></Data>
</Node>
</Node>
</Node>
<Node><Sub> PATIENTINFOREGISTER</Sub>
<Node><Sub>87</Sub>
<Node><Sub>99</Sub>
<Data></Data>
</Node>
</Node>
</Node>
</Node>
</Node>
</Node>
</Global>


<Global>
<Node><Sub>^EnsLib.PubSub.TargetD</Sub>
<Data>87</Data>
<Node><Sub>19</Sub>
<DataBase64>HAF+RW5zTGliLlB1YlN1Yi5TdWJzY3JpYmVyfgIBAQkBU2F2ZUNEQSIBSENDLlNWUi5Qcm9kLkJP
LlNhdmVDREFPcGVyYXRpb24BAgE=
</DataBase64>
<Node><Sub>Subscriber</Sub>
<DataBase64>BgFITEhU
</DataBase64>
</Node>
</Node>
<Node><Sub>20</Sub>
<DataBase64>HAF+RW5zTGliLlB1YlN1Yi5TdWJzY3JpYmVyfgIBAQsBQWNjZXNzQ0RBJAFIQ0MuU1ZSLlByb2Qu
Qk8uQWNjZXNzQ0RBT3BlcmF0aW9uAQIB
</DataBase64>
<Node><Sub>Subscriber</Sub>
<DataBase64>BgFITEhU
</DataBase64>
</Node>
</Node>
<Node><Sub>21</Sub>
<DataBase64>HAF+RW5zTGliLlB1YlN1Yi5TdWJzY3JpYmVyfgIBAQ0BUmV0cmlldmVDREEmAUhDQy5TVlIuUHJv
ZC5CTy5SZXRyaWV2ZUNEQU9wZXJhdGlvbgECAQ==
</DataBase64>
<Node><Sub>Subscriber</Sub>
<DataBase64>BgFITEhU
</DataBase64>
</Node>
</Node>
<Node><Sub>87</Sub>
<DataBase64>HAF+RW5zTGliLlB1YlN1Yi5TdWJzY3JpYmVyfgIBAQUBRU1SBQFFTVIBAgE=
</DataBase64>
<Node><Sub>Subscriber</Sub>
<DataBase64>BgFITEhU
</DataBase64>
</Node>
</Node>
</Node>
</Global>


<Global>
<Node><Sub>^EnsLib.PubSub.TargetI</Sub>
<Node><Sub>NameIdx</Sub>
<Node><Sub>HLHT</Sub>
<Node><Sub> ACCESSCDA</Sub>
<Node><Sub>20</Sub>
<Data>~EnsLib.PubSub.Subscriber~</Data>
</Node>
</Node>
<Node><Sub> EMR</Sub>
<Node><Sub>87</Sub>
<Data>~EnsLib.PubSub.Subscriber~</Data>
</Node>
</Node>
<Node><Sub> RETRIEVECDA</Sub>
<Node><Sub>21</Sub>
<Data>~EnsLib.PubSub.Subscriber~</Data>
</Node>
</Node>
<Node><Sub> SAVECDA</Sub>
<Node><Sub>19</Sub>
<Data>~EnsLib.PubSub.Subscriber~</Data>
</Node>
</Node>
</Node>
</Node>
</Node>
</Global>
</Export>
